[{"adm0_name":"Madagascar","adm1_name":"Androy","adm0_code":600,"adm1_code":167016,"adm2_code":77130,"population":758655,"loss":68714.5752045947},{"adm0_name":"Madagascar","adm1_name":"Anosy","adm0_code":300,"adm1_code":83510,"adm2_code":38567,"population":14261,"loss":46.2903117252},{"adm0_name":"Madagascar","adm1_name":"Atsimo Andrefana","adm0_code":450,"adm1_code":125268,"adm2_code":57855,"population":103817,"loss":45912.8892423658},{"adm0_name":"Mozambique","adm1_name":"Inhambane","adm0_code":680,"adm1_code":8456,"adm2_code":87462,"population":66173,"loss":9213.5488695284},{"adm0_name":"Mozambique","adm1_name":"Nampula","adm0_code":680,"adm1_code":8472,"adm2_code":87580,"population":682095,"loss":110186.6454178159},{"adm0_name":"Mozambique","adm1_name":"Sofala","adm0_code":1190,"adm1_code":14840,"adm2_code":196829,"population":182459,"loss":9055.937472053},{"adm0_name":"Mozambique","adm1_name":"Zambezia","adm0_code":2720,"adm1_code":33952,"adm2_code":394574,"population":1842414,"loss":452341.6702072375}]