[{"adm0_name":"Madagascar","adm1_name":"Atsimo Andrefana","adm2_name":"Ampanihy","adm0_code":150,"adm1_code":41756,"adm2_code":19277,"population":1814,"loss":2118.8540254738},{"adm0_name":"Madagascar","adm1_name":"Atsimo Andrefana","adm2_name":"Betioky","adm0_code":150,"adm1_code":41756,"adm2_code":19284,"population":665,"loss":2070.5501673686},{"adm0_name":"Madagascar","adm1_name":"Atsimo Andrefana","adm2_name":"Morombe","adm0_code":150,"adm1_code":41756,"adm2_code":19289,"population":2,"loss":83.4958939986},{"adm0_name":"Madagascar","adm1_name":"Atsimo Andrefana","adm2_name":"Toliary II","adm0_code":150,"adm1_code":41756,"adm2_code":19294,"population":141,"loss":743.6453996138}]