[{"adm0_name":"Mauritius","adm1_name":"Administrative unit not available","adm2_name":"Administrative unit not available","adm0_code":160,"adm1_code":2017,"adm2_code":19535,"population":0,"loss":0.0024613661},{"adm0_name":"Mauritius","adm1_name":"Flacq","adm2_name":"Administrative unit not available","adm0_code":160,"adm1_code":2019,"adm2_code":19537,"population":1227,"loss":0.0104974803},{"adm0_name":"Mauritius","adm1_name":"Grand Port","adm2_name":"Administrative unit not available","adm0_code":160,"adm1_code":2020,"adm2_code":19538,"population":180,"loss":0.0004509425}]