[{"adm0_name":"Madagascar","adm1_name":"Alaotra Mangoro","adm0_code":750,"adm1_code":208750,"adm2_code":96301,"population":1138448,"loss":25210242.0464913137},{"adm0_name":"Madagascar","adm1_name":"Amoron'i Mania","adm0_code":600,"adm1_code":167004,"adm2_code":76877,"population":659851,"loss":2255071.1671525305},{"adm0_name":"Madagascar","adm1_name":"Analamanga","adm0_code":1200,"adm1_code":334016,"adm2_code":153523,"population":4709850,"loss":23836442.3442576975},{"adm0_name":"Madagascar","adm1_name":"Analanjirofo","adm0_code":1050,"adm1_code":292271,"adm2_code":134872,"population":1494847,"loss":68556458.7015491575},{"adm0_name":"Madagascar","adm1_name":"Androy","adm0_code":150,"adm1_code":41754,"adm2_code":19279,"population":738,"loss":1.8119409938},{"adm0_name":"Madagascar","adm1_name":"Anosy","adm0_code":450,"adm1_code":125265,"adm2_code":57852,"population":193512,"loss":14940.9324820857},{"adm0_name":"Madagascar","adm1_name":"Atsimo Atsinanana","adm0_code":750,"adm1_code":208785,"adm2_code":96135,"population":1275114,"loss":522348.1205444298},{"adm0_name":"Madagascar","adm1_name":"Atsinanana","adm0_code":900,"adm1_code":250548,"adm2_code":115606,"population":1012577,"loss":4214426.1697828714},{"adm0_name":"Madagascar","adm1_name":"Betsiboka","adm0_code":450,"adm1_code":125277,"adm2_code":57747,"population":325742,"loss":1718501.5319044336},{"adm0_name":"Madagascar","adm1_name":"Boeny","adm0_code":900,"adm1_code":250560,"adm2_code":115491,"population":977327,"loss":591174.3732294452},{"adm0_name":"Madagascar","adm1_name":"Bongolava","adm0_code":300,"adm1_code":83522,"adm2_code":38402,"population":561588,"loss":370269.9211398251},{"adm0_name":"Madagascar","adm1_name":"Diana","adm0_code":750,"adm1_code":208810,"adm2_code":96037,"population":766076,"loss":849914.990406348},{"adm0_name":"Madagascar","adm1_name":"Haute Matsiatra","adm0_code":750,"adm1_code":208815,"adm2_code":96094,"population":1082925,"loss":1176606.7607902151},{"adm0_name":"Madagascar","adm1_name":"Ihorombe","adm0_code":450,"adm1_code":125292,"adm2_code":57673,"population":320511,"loss":71787.7526341029},{"adm0_name":"Madagascar","adm1_name":"Itasy","adm0_code":450,"adm1_code":125295,"adm2_code":57599,"population":737377,"loss":2826717.0284618028},{"adm0_name":"Madagascar","adm1_name":"Melaky","adm0_code":450,"adm1_code":125298,"adm2_code":57734,"population":35129,"loss":1423.9865262225},{"adm0_name":"Madagascar","adm1_name":"Menabe","adm0_code":450,"adm1_code":125301,"adm2_code":57855,"population":10036,"loss":14616.19768772},{"adm0_name":"Madagascar","adm1_name":"Sava","adm0_code":600,"adm1_code":167072,"adm2_code":76835,"population":1100084,"loss":10278232.8247151151},{"adm0_name":"Madagascar","adm1_name":"Sofia","adm0_code":1050,"adm1_code":292383,"adm2_code":134706,"population":1606641,"loss":34929439.1650222689},{"adm0_name":"Madagascar","adm1_name":"Vakinakaratra","adm0_code":900,"adm1_code":250620,"adm2_code":115162,"population":1799175,"loss":13663906.7369990237},{"adm0_name":"Madagascar","adm1_name":"Vatovavy Fitovinany","adm0_code":900,"adm1_code":250626,"adm2_code":115373,"population":1888525,"loss":1119087.8967751823},{"adm0_name":"Mauritius","adm1_name":"Savanne","adm0_code":160,"adm1_code":2026,"adm2_code":19544,"population":1495,"loss":125976.7035328261},{"adm0_name":"R\u00e9union","adm1_name":"Arrondissement_du_vent","adm0_code":206,"adm1_code":2590,"adm2_code":25273,"population":124003,"loss":2795294.0504267919},{"adm0_name":"R\u00e9union","adm1_name":"Arrondissement_souse_le_vent","adm0_code":206,"adm1_code":2591,"adm2_code":25274,"population":187469,"loss":29636199.3103585057}]