{"records": [{"adm0_name": "Madagascar", "adm0_code": 150, "population": 61708, "loss": 2.3093311374, "wind_cat": {"0": 61708}, "adm1": [{"adm1_name": "Bongolava", "adm1_code": 41761, "population": 56350, "loss": 1.951944114, "wind_cat": {"0": 56350}, "adm2": [{"adm2_name": "Tsiroanomandidy", "adm2_code": 19203, "population": 56350, "loss": 1.951944114, "wind_cat": {"0": 56350}}]}, {"adm1_name": "Melaky", "adm1_code": 41766, "population": 187, "loss": 0.0089332811, "wind_cat": {"0": 187}, "adm2": [{"adm2_name": "Ambatomainty", "adm2_code": 19237, "population": 75, "loss": 0.0009618521, "wind_cat": {"0": 75}}, {"adm2_name": "Morafenobe", "adm2_code": 19254, "population": 112, "loss": 0.007971429, "wind_cat": {"0": 112}}]}, {"adm1_name": "Menabe", "adm1_code": 41767, "population": 5171, "loss": 0.3484537423, "wind_cat": {"0": 5171}, "adm2": [{"adm2_name": "Miandrivazo", "adm2_code": 19288, "population": 5171, "loss": 0.3484537423, "wind_cat": {"0": 5171}}]}]}]}